{
  "5782683757": {
    "coins": 99999999999999999999999941,
    "username": "RBXTelega"
  },
  "8284729373": {
    "coins": 999999999999999999999787059,
    "username": "reservRBXTelega"
  },
  "6545137320": {
    "coins": 578
  },
  "6805997690": {
    "coins": 199
  },
  "8041353323": {
    "coins": 6
  },
  "5862095051": {
    "coins": 1039
  },
  "7349628643": {
    "coins": 63
  },
  "6657988816": {
    "coins": 5
  },
  "5310333143": {
    "coins": 1
  },
  "6644275327": {
    "coins": 76
  },
  "8182579353": {
    "coins": 569
  },
  "6483732727": {
    "coins": 71
  },
  "7648592847": {
    "coins": 3
  },
  "5375431937": {
    "coins": 67
  }
}